odoo/addons/stock_picking_whole_scrap/README.rst
odoo/addons/stock_picking_whole_scrap/__init__.py
odoo/addons/stock_picking_whole_scrap/__manifest__.py
odoo/addons/stock_picking_whole_scrap/i18n/es.po
odoo/addons/stock_picking_whole_scrap/i18n/pt_BR.po
odoo/addons/stock_picking_whole_scrap/i18n/sl.po
odoo/addons/stock_picking_whole_scrap/i18n/stock_picking_whole_scrap.pot
odoo/addons/stock_picking_whole_scrap/models/__init__.py
odoo/addons/stock_picking_whole_scrap/models/stock_picking.py
odoo/addons/stock_picking_whole_scrap/readme/CONTRIBUTORS.rst
odoo/addons/stock_picking_whole_scrap/readme/DESCRIPTION.rst
odoo/addons/stock_picking_whole_scrap/readme/USAGE.rst
odoo/addons/stock_picking_whole_scrap/static/description/icon.png
odoo/addons/stock_picking_whole_scrap/static/description/index.html
odoo/addons/stock_picking_whole_scrap/tests/__init__.py
odoo/addons/stock_picking_whole_scrap/tests/test_stock_picking_whole_scrap.py
odoo/addons/stock_picking_whole_scrap/views/stock_picking_views.xml
odoo/addons/stock_picking_whole_scrap/wizards/__init__.py
odoo/addons/stock_picking_whole_scrap/wizards/stock_picking_whole_scrap.py
odoo/addons/stock_picking_whole_scrap/wizards/stock_picking_whole_scrap.xml
odoo12_addon_stock_picking_whole_scrap-12.0.1.0.0.99.dev8.dist-info/METADATA
odoo12_addon_stock_picking_whole_scrap-12.0.1.0.0.99.dev8.dist-info/WHEEL
odoo12_addon_stock_picking_whole_scrap-12.0.1.0.0.99.dev8.dist-info/top_level.txt
odoo12_addon_stock_picking_whole_scrap-12.0.1.0.0.99.dev8.dist-info/RECORD
